{
	"Description": {
		"Id": "AbilityDefG5T",
		"Name": "INTENSIFY FIREPOWER",
		"Details": "ACTION: Cannot be used if you have moved this turn. Intentionally pillbox this tank, losing all ability to move this turn. In exchange, gain +30% damage this turn. 4 turn cooldown, does not end the turn. <b><color=#099ff2>Costs 30 Resolve to use!</color></b>",
		"Icon": "hypersonic-bolt"
	},
	"DisplayParams": "ShowInMWTRay",
	"ReqSkill": "Gunnery",
	"ReqSkillLevel": 5,
	"ActivationTime": "ConsumedByMovement",
	"ActivationCooldown": 4,
	"Targeting": "ActorSelf",
	"ResolveCost": 30,
	"EffectData": [
		{
			"durationData": {
				"duration": 1,
				"ticksOnActivations": true,
				"useActivationsOfTarget": true,
				"stackLimit": 1
			},
			"targetingData": {
				"effectTriggerType": "OnActivation",
				"effectTargetType": "Creator",
				"forcePathRebuild": true,
				"showInStatusPanel": true
			},
			"effectType": "StatisticEffect",
			"Description": {
				"Id": "StatusEffect-IntenseCruise",
				"Name": "Intensified Firepower",
				"Details": "This unit can not move this turn but deals +30% damage for this turn.",
				"Icon": "hypersonic-bolt"
			},
			"statisticData": {
				"statName": "CruiseSpeed",
				"operation": "Float_Multiply",
				"modValue": "0.01",
				"modType": "System.Single"
			},
			"nature": "Buff"
		},
		{
			"durationData": {
				"duration": 1,
				"ticksOnActivations": true,
				"useActivationsOfTarget": true,
				"stackLimit": 1
			},
			"targetingData": {
				"effectTriggerType": "OnActivation",
				"effectTargetType": "Creator",
				"forcePathRebuild": true,
				"showInStatusPanel": false
			},
			"effectType": "StatisticEffect",
			"Description": {
				"Id": "StatusEffect-IntenseFlank",
				"Name": "Intensified Firepower",
				"Details": "This unit can not move this turn but deals +30% damage for this turn.",
				"Icon": "hypersonic-bolt"
			},
			"statisticData": {
				"statName": "FlankSpeed",
				"operation": "Float_Multiply",
				"modValue": "0.01",
				"modType": "System.Single"
			},
			"nature": "Buff"
		},
		{
			"durationData": {
				"duration": 1,
				"ticksOnActivations": true,
				"useActivationsOfTarget": true,
				"stackLimit": 1
			},
			"targetingData": {
				"effectTriggerType": "OnActivation",
				"effectTargetType": "Creator",
				"forcePathRebuild": true,
				"showInStatusPanel": false
			},
			"effectType": "StatisticEffect",
			"Description": {
				"Id": "StatusEffect-IntenseWalk",
				"Name": "Intensified Firepower",
				"Details": "This unit can not move this turn but deals +30% damage for this turn.",
				"Icon": "hypersonic-bolt"
			},
			"statisticData": {
				"statName": "WalkSpeed",
				"operation": "Float_Multiply",
				"modValue": "0.01",
				"modType": "System.Single"
			},
			"nature": "Buff"
		},
		{
			"durationData": {
				"duration": 1,
				"ticksOnActivations": true,
				"useActivationsOfTarget": true,
				"stackLimit": 1
			},
			"targetingData": {
				"effectTriggerType": "OnActivation",
				"effectTargetType": "Creator",
				"forcePathRebuild": true,
				"showInStatusPanel": false
			},
			"effectType": "StatisticEffect",
			"Description": {
				"Id": "StatusEffect-IntenseRun",
				"Name": "Intensified Firepower",
				"Details": "This unit can not move this turn but deals +30% damage for this turn.",
				"Icon": "hypersonic-bolt"
			},
			"statisticData": {
				"statName": "CBTBE_RunMultiMod",
				"operation": "Float_Multiply",
				"modValue": "0.01",
				"modType": "System.Single"
			},
			"nature": "Buff"
		},
		{
			"durationData": {
				"duration": 1,
				"ticksOnActivations": true,
				"useActivationsOfTarget": true,
				"stackLimit": 1
			},
			"targetingData": {
				"effectTriggerType": "OnActivation",
				"effectTargetType": "Creator",
				"forcePathRebuild": true,
				"showInStatusPanel": false
			},
			"effectType": "StatisticEffect",
			"Description": {
				"Id": "StatusEffect-IntenseJump",
				"Name": "Intensified Firepower",
				"Details": "This unit can not move this turn but deals +30% damage for this turn.",
				"Icon": "hypersonic-bolt"
			},
			"statisticData": {
				"statName": "JumpDistanceMultiplier",
				"operation": "Float_Multiply",
				"modValue": "0.01",
				"modType": "System.Single"
			},
			"nature": "Buff"
		},
		{
			"durationData": {
				"duration": 1,
				"ticksOnActivations": true,
				"useActivationsOfTarget": true,
				"stackLimit": 1
			},
			"targetingData": {
				"effectTriggerType": "OnActivation",
				"effectTargetType": "Creator",
				"showInStatusPanel": false
			},
			"effectType": "StatisticEffect",
			"Description": {
				"Id": "StatusEffect-IntenseDmgBoost",
				"Name": "Intensified Firepower",
				"Details": "This unit can not move this turn but deals +30% damage for this turn.",
				"Icon": "hypersonic-bolt"
			},
			"statisticData": {
				"statName": "DamagePerShot",
				"operation": "Float_Multiply",
				"modValue": "1.3",
				"modType": "System.Single",
				"additionalRules": "NotSet",
				"targetCollection": "Weapon",
				"targetWeaponCategory": "NotSet",
				"targetWeaponType": "NotSet",
				"targetAmmoCategory": "NotSet",
				"targetWeaponSubType": "NotSet"
			},
			"nature": "Buff"
		}
	],
	"IsPrimaryAbility": true,
	"Priority": 9
}