{
    "Description": {
        "Id": "3064-04-07",
        "Name": "MercNews Broadcast",
        "Details": "OMIKO KURITA ASSASSINATED IN THE DRAGONS DEN!\r\n\n\nLuthien, Draconis Combine: The entire Draconis Combine is in mourning over the death of the beloved daughter of Theodore Kurita, assassinated in the heart of the Kuritan palace on Luthien. Combine security forces have shut down all interstellar travel within Combine space in an attempt to apprehend the assassin, and all Combine citizens are compelled to assist security forces however possible. The assassin’s motive is as yet unknown, but speculations run from the domestic Kokuryu-kai to any number of foreign entities.\r\n\n\nPlease stay tuned for a word from our sponsor.",
        "Icon": "uixTxrSpot_ComputerScreen.png"
    },
    "Scope": "Company",
    "Weight": 0,
    "Requirements": {
        "Scope": "Company",
        "RequirementTags": {
            "items": null,
            "tagSetSourceFile": ""
        },
        "ExclusionTags": {
            "items": null,
            "tagSetSourceFile": ""
        },
        "RequirementComparisons": []
    },
    "AdditionalRequirements": [],
    "AdditionalObjects": [],
    "Options": [
        {
            "Description": {
                "Id": "continue",
                "Name": "Continue.",
                "Details": "Broadcast continues",
                "Icon": ""
            },
            "RequirementList": [],
            "ResultSets": [
                {
                    "Description": {
                        "Id": "continue1",
                        "Name": "MercNews Broadcast",
                        "Details": "Marian Arms Incorporated: Exercitu Caesaris©\r\n\n\nNewly developed by the foremost arms manufacturer in the Marian Hegemeny, MAI is proud to announce the availability of the Rocket Launcher. Offered in racks of 10, 15, and 20, the Rocket Launcher is a single-shot, unguided missile pack that can be fitted to nearly any BattleMech<sup>1</sup>. Quick to build and cheap to buy, Rocket Launchers are the perfect weapons for the MechWarrior on a budget and are a great addition to any loadout with a few tons to spare. Contact the nearest Marian Arms Incorporated representative to buy yours today! \r\n\n\n<sup>1</sup><sub>Marian Arms Incorporated is not responsible for ensuring this product is compatible with your equipment.</sub>",
                        "Icon": ""
                    },
                    "Weight": 100,
                    "Results": [
                        {
                            "Scope": "Company",
                            "Requirements": null,
                            "AddedTags": {
                                "items" : [
                                ],
                                "tagSetSourceFile" : ""
                            
                            },
                            "RemovedTags": {
                                "items": null,
                                "tagSetSourceFile": ""
                            },
                            "Stats": null,
                            "Actions": null,
                            "ForceEvents": null,
                            "TemporaryResult": false,
                            "ResultDuration": 0
                        }
                    ]
                }
            ],
            "Requirements": {
                "Scope": "Company",
                "RequirementTags": {
                    "items": null,
                    "tagSetSourceFile": ""
                },
                "ExclusionTags": {
                    "items": null,
                    "tagSetSourceFile": ""
                },
                "RequirementComparisons": []
            }
        }
    ],
    "PublishState": "PUBLISHED",
    "ValidationState": "UNTESTED",
    "EventType": "UNSELECTABLE"
}
