{
    "Description" : {
        "Id" : "tbone_event_co_raceBlaze_Apoc_HL",
        "Name" : "Apocalypse Race: There Can Be Only One!",
        "Details" : "You have a message from [[SCN_MW,{SCN_MW.Callsign}]]. Apparently we've arrived in the system just in time for a race, and {SCN_MW.SUBJ} needs to know whether to sign up:\r\n\r\n<i><b>Commander, if we're going to do this race, there are a few things you need to know. This one takes place in the [[DM.BaseDescriptionDefs[BiomeHighlands],highlands]], so we have a few options. I can push hard and drive aggressively, but we'll probably banged up pretty good on some of those rocky outcroppings and ravines. On the other hand, I can play it a bit safer and hope to make up the time in the straightaways. Like most of these races, there's also an optional \"shortcut\" route; this one appears to run through a dense boulder field with a lot of tight turns. Just let me know how you'd like to proceed, and I'll get things ready to go. Of course if we don't have time, I understand.</i></b>",
        "Icon" : "uixTxrSpot_ComputerScreen.png"
    },
    "Scope" : "Company",
    "Weight" : 10000,
    "Requirements" : {
        "Scope" : "Company",
        "RequirementTags" : {
            "tagSetSourceFile" : "",
            "items" : []
        },
        "ExclusionTags" : {
            "tagSetSourceFile" : "",
            "items" : [
                "finished_Blaze"
            ]
        },
        "RequirementComparisons" : [
            {
                "obj" : "Travel",
                "op" : "Equal",
                "val" : 0,
                "valueConstant" : "0"
            }
        ]
    },
    "AdditionalRequirements" : [
        {
            "Scope" : "StarSystem",
            "RequirementTags" : {
                "tagSetSourceFile" : "",
                "items" : [
                    "planet_climate_terran"
                ]
            },
            "ExclusionTags" : {
                "tagSetSourceFile" : "",
                "items" : []
            },
            "RequirementComparisons" : []
        }
    ],
    "AdditionalObjects" : [
        {
            "Scope" : "SecondaryMechWarrior",
            "Requirements" : {
                "Scope" : "SecondaryMechWarrior",
                "RequirementTags" : {
                    "tagSetSourceFile" : "Tags/PilotTags",
                    "items" : [
                        "name_Blaze",
                        "racer_apocalypse"
                    ]
                },
                "ExclusionTags" : {
                    "tagSetSourceFile" : "",
                    "items" : [
                        "race_highland"
                    ]
                },
                "RequirementComparisons" : [
                    {
                        "obj" : "Injuries",
                        "op" : "LessThanOrEqual",
                        "val" : 0,
                        "valueConstant" : "0"
                    }
                ]
            }
        }
    ],
    "Options" : [
        {
            "Description" : {
                "Id" : "outcome_0",
                "Name" : "Drive aggressively",
                "Details" : "-",
                "Icon" : null
            },
            "RequirementList" : [],
            "ResultSets" : [
                {
                    "Description" : {
                        "Id" : "outcome_0_0",
                        "Name" : "Drive aggressively.",
                        "Details" : "The rocky trails of the [[DM.BaseDescriptionDefs[BiomeHighlands],highlands]] were no match for the rugged dependability of the [[DM.BaseDescriptionDefs[TBoneLoreApocalypseWR],Apocalypse]]. Although some of the other racers had faster rigs, most of them suffered from mechanical breakdowns from the rough terrain, and by the end [[SCN_MW,{SCN_MW.Callsign}]] came out ahead with a generous lead.",
                        "Icon" : null
                    },
                    "Weight" : 100,
                    "Results" : [
                        {
                            "Scope" : "Company",
                            "Requirements" : null,
                            "AddedTags" : {
                                "tagSetSourceFile" : "",
                                "items" : []
                            },
                            "RemovedTags" : {
                                "tagSetSourceFile" : "",
                                "items" : []
                            },
                            "Stats" : [
                                {
                                    "typeString" : "System.Int32",
                                    "name" : "Morale",
                                    "value" : "1",
                                    "set" : false,
                                    "valueConstant" : null
                                },
                                {
                                    "typeString" : "System.Int32",
                                    "name" : "Funds",
                                    "value" : "100000",
                                    "set" : false,
                                    "valueConstant" : null
                                },
                                {
                                    "typeString" : "System.Int32",
                                    "name" : "RaceWins",
                                    "value" : "1",
                                    "set" : false,
                                    "valueConstant" : null
                                }
                            ],
                            "Actions" : null,
                            "ForceEvents" : null,
                            "TemporaryResult" : false,
                            "ResultDuration" : 0
                        },
                        {
                            "Scope" : "SecondaryMechWarrior",
                            "Requirements" : null,
                            "AddedTags" : {
                                "tagSetSourceFile" : "",
                                "items" : [
                                    "race_highland"
                                ]
                            },
                            "RemovedTags" : {
                                "tagSetSourceFile" : "",
                                "items" : []
                            },
                            "Stats" : null,
                            "Actions" : null,
                            "ForceEvents" : null,
                            "TemporaryResult" : false,
                            "ResultDuration" : 0
                        }
                    ]
                }
            ],
            "Requirements" : {
                "Scope" : "Company",
                "RequirementTags" : {
                    "tagSetSourceFile" : "",
                    "items" : []
                },
                "ExclusionTags" : {
                    "tagSetSourceFile" : "",
                    "items" : []
                },
                "RequirementComparisons" : []
            }
        },
        {
            "Description" : {
                "Id" : "outcome_1",
                "Name" : "Play it safe.",
                "Details" : "-",
                "Icon" : null
            },
            "RequirementList" : [],
            "ResultSets" : [
                {
                    "Description" : {
                        "Id" : "outcome_1_0",
                        "Name" : "Play it safe.",
                        "Details" : "Although [[SCN_MW,{SCN_MW.Callsign}]] did her best, the [[DM.BaseDescriptionDefs[TBoneLoreApocalypseWR],Apocalypse]] just wasn't fast enough to keep up with the other racers. Even though the rough terrain slowed the speedier racers to crawl in spots, they were able to leap back into the lead once the trail cleared, leaving [[SCN_MW,{SCN_MW.Callsign}]] in the middle of the pack.",
                        "Icon" : null
                    },
                    "Weight" : 100,
                    "Results" : [
                        {
                            "Scope" : "Company",
                            "Requirements" : null,
                            "AddedTags" : {
                                "tagSetSourceFile" : "",
                                "items" : []
                            },
                            "RemovedTags" : {
                                "tagSetSourceFile" : "",
                                "items" : []
                            },
                            "Stats" : [
                                {
                                    "typeString" : "System.Int32",
                                    "name" : "RaceWins",
                                    "value" : "-1",
                                    "set" : false,
                                    "valueConstant" : null
                                }
                            ],
                            "Actions" : null,
                            "ForceEvents" : null,
                            "TemporaryResult" : false,
                            "ResultDuration" : 0
                        },
                        {
                            "Scope" : "SecondaryMechWarrior",
                            "Requirements" : null,
                            "AddedTags" : {
                                "tagSetSourceFile" : "",
                                "items" : [
                                    "race_highland"
                                ]
                            },
                            "RemovedTags" : {
                                "tagSetSourceFile" : "",
                                "items" : []
                            },
                            "Stats" : null,
                            "Actions" : null,
                            "ForceEvents" : null,
                            "TemporaryResult" : false,
                            "ResultDuration" : 0
                        }
                    ]
                }
            ],
            "Requirements" : {
                "Scope" : "Company",
                "RequirementTags" : {
                    "tagSetSourceFile" : "",
                    "items" : []
                },
                "ExclusionTags" : {
                    "tagSetSourceFile" : "",
                    "items" : []
                },
                "RequirementComparisons" : []
            }
        },
        {
            "Description" : {
                "Id" : "outcome_2",
                "Name" : "Take the shortcut.",
                "Details" : "-",
                "Icon" : null
            },
            "RequirementList" : [],
            "ResultSets" : [
                {
                    "Description" : {
                        "Id" : "outcome_2_0",
                        "Name" : "Take the shortcut.",
                        "Details" : "At first glance, the shortcut through the boulder field looked like a sure bet. Unfortunately, the [[DM.BaseDescriptionDefs[TBoneLoreApocalypseWR],Apocalypse]] has a wide stance and a long wheelbase, and by the time you realized your mistake, [[SCN_MW,{SCN_MW.Callsign}]] had the big 6x6 wedged between two boulders and was unable to finish the race. At least the cost of the wrecker was included in the race fees...",
                        "Icon" : null
                    },
                    "Weight" : 100,
                    "Results" : [
                        {
                            "Scope" : "Company",
                            "Requirements" : null,
                            "AddedTags" : {
                                "tagSetSourceFile" : "",
                                "items" : []
                            },
                            "RemovedTags" : {
                                "tagSetSourceFile" : "",
                                "items" : []
                            },
                            "Stats" : [
                                {
                                    "typeString" : "System.Int32",
                                    "name" : "Morale",
                                    "value" : "-1",
                                    "set" : false,
                                    "valueConstant" : null
                                },
                                {
                                    "typeString" : "System.Int32",
                                    "name" : "Funds",
                                    "value" : "-100000",
                                    "set" : false,
                                    "valueConstant" : null
                                },
                                {
                                    "typeString" : "System.Int32",
                                    "name" : "RaceWins",
                                    "value" : "-1",
                                    "set" : false,
                                    "valueConstant" : null
                                }
                            ],
                            "Actions" : null,
                            "ForceEvents" : null,
                            "TemporaryResult" : false,
                            "ResultDuration" : 0
                        },
                        {
                            "Scope" : "SecondaryMechWarrior",
                            "Requirements" : null,
                            "AddedTags" : {
                                "tagSetSourceFile" : "",
                                "items" : [
                                    "race_highland"
                                ]
                            },
                            "RemovedTags" : {
                                "tagSetSourceFile" : "",
                                "items" : []
                            },
                            "Stats" : null,
                            "Actions" : null,
                            "ForceEvents" : null,
                            "TemporaryResult" : false,
                            "ResultDuration" : 0
                        }
                    ]
                }
            ],
            "Requirements" : {
                "Scope" : "Company",
                "RequirementTags" : {
                    "tagSetSourceFile" : "",
                    "items" : []
                },
                "ExclusionTags" : {
                    "tagSetSourceFile" : "",
                    "items" : []
                },
                "RequirementComparisons" : []
            }
        },
        {
            "Description" : {
                "Id" : "outcome_3",
                "Name" : "Hold off on racing for now.",
                "Details" : "Hold off on racing for now.",
                "Icon" : null
            },
            "RequirementList" : [],
            "ResultSets" : [
                {
                    "Description" : {
                        "Id" : "outcome_3_0",
                        "Name" : "no race.",
                        "Details" : "Blaze knows that contracts are more important than racing. Besides, there are plenty of other races to run.",
                        "Icon" : null
                    },
                    "Weight" : 100,
                    "Results" : []
                }
            ],
            "Requirements" : {
                "Scope" : "Company",
                "RequirementTags" : {
                    "tagSetSourceFile" : "",
                    "items" : []
                },
                "ExclusionTags" : {
                    "tagSetSourceFile" : "",
                    "items" : []
                },
                "RequirementComparisons" : []
            }
        }
    ],
    "PublishState" : "PUBLISHED",
    "ValidationState" : "UNTESTED",
    "EventType" : "NORMAL",
    "OneTimeEvent" : false,
    "Tags" : {
        "tagSetSourceFile" : "tags/EventTags",
        "items" : []
    }
}