{
   "Locations" : [
		{
			"Location" : "Front",
			"CurrentArmor" : 125,
			"CurrentInternalStructure" : 15,
			"AssignedArmor" : 125,
			"DamageLevel" : "Functional"
		},
		{
			"Location" : "Left",
			"CurrentArmor" : 130,
			"CurrentInternalStructure" : 15,
			"AssignedArmor" : 130,
			"DamageLevel" : "Functional"
		},
		{
			"Location" : "Right",
			"CurrentArmor" : 130,
			"CurrentInternalStructure" : 15,
			"AssignedArmor" : 130,
			"DamageLevel" : "Functional"
		},
		{
			"Location" : "Rear",
			"CurrentArmor" : 125,
			"CurrentInternalStructure" : 15,
			"AssignedArmor" : 125,
			"DamageLevel" : "Functional"
		},
		{
			"Location" : "Turret",
			"CurrentArmor" : 125,
			"CurrentInternalStructure" : 15,
			"AssignedArmor" : 125,
			"DamageLevel" : "Functional"
		}
   ]
}