{
  "Description": {
    "Id": "starsystemdef_Tarol",
    "Name": "Tarol",
    "Details": "Settled at some point prior to the end of the Age of War, Tarol IV was a member of the Magistracy of Canopus when an SLDF task force under the command of Captain-General Marion Marik was assigned to conquer the Magistracy of Canopus in 2577.",
    "Icon": ""
  },
  "Position": {
    "x": -229.505,
    "y": -399.334,
    "z": 0
  },
  "Tags": {
    "items": [
      "planet_name_tarol",
      "planet_size_small",
      "planet_climate_desert",
      "planet_pop_none",
      "planet_industry_agriculture",
      "planet_industry_aquaculture",
      "planet_faction_magistracyofcanopus"
    ],
    "tagSetSourceFile": ""
  },
  "SupportedBiomes": [
    "desertParched"
  ],
  "MapRequiredTags": {
    "items": [],
    "tagSetSourceFile": ""
  },
  "MapExcludedTags": {
    "items": [],
    "tagSetSourceFile": ""
  },
  "FuelingStation": false,
  "JumpDistance": 11,
  "ownerID": "MagistracyOfCanopus",
  "ShopRefreshRate": 0,
  "ShopMaxInventory": 0,
  "ShopMaxSpecials": 9,
  "SystemInfluence": [
    {
      "Faction": "NoFaction",
      "Influence": 0
    },
    {
      "Faction": "Davion",
      "Influence": 0
    },
    {
      "Faction": "Liao",
      "Influence": 0
    },
    {
      "Faction": "Kurita",
      "Influence": 0
    },
    {
      "Faction": "Marik",
      "Influence": 0
    },
    {
      "Faction": "Steiner",
      "Influence": 0
    },
    {
      "Faction": "TaurianConcordat",
      "Influence": 0
    },
    {
      "Faction": "MagistracyOfCanopus",
      "Influence": 0
    },
    {
      "Faction": "AuriganDirectorate",
      "Influence": 0
    },
    {
      "Faction": "AuriganRestoration",
      "Influence": 0
    },
    {
      "Faction": "ComStar",
      "Influence": 0
    },
    {
      "Faction": "MercenaryReviewBoard",
      "Influence": 0
    },
    {
      "Faction": "AuriganPirates",
      "Influence": 0
    },
    {
      "Faction": "AuriganMercenaries",
      "Influence": 0
    }
  ],
  "TravelRequirements": [
    {
      "Scope": "Company",
      "RequirementTags": {
        "items": [
          "map_travel_2a"
        ],
        "tagSetSourceFile": ""
      },
      "ExclusionTags": {
        "items": [],
        "tagSetSourceFile": ""
      },
      "RequirementComparisons": []
    }
  ],
  "StarPosition": null,
  "StarType": "K",
  "Depletable": false,
  "UseSystemRoninHiringChance": false,
  "RoninHiringChance": 0,
  "UseMaxContractOverride": false,
  "MaxContractOverride": 0,
  "SystemShopItems": [
    "itemCollection_major_MagistracyOfCanopus",
    "itemCollection_shop_industrial",
    "itemCollection_shop_research"
  ],
  "factionShopOwnerID": "MagistracyOfCanopus",
  "FactionShopItems": [
    "itemCollection_faction_MagistracyOfCanopus"
  ],
  "BlackMarketShopItems": null,
  "CoreSystemID": "starsystemdef_Tarol",
  "StartingSystemModes": [
    "KAMEA_CAMPAIGN",
    "CAREER",
    "NONE"
  ],
  "DefaultDifficulty": 8,
  "DifficultyList": [],
  "DifficultyModes": [],
  "contractEmployerIDs": [
    "MagistracyOfCanopus",
    "Locals"
  ],
  "contractTargetIDs": [
    "Liao",
    "Marik",
    "Marian",
	"TaurianConcordat",
    "AuriganPirates",
	"AuriganRestoration",
    "ComStar"
  ]
}