{
    "Description": {
        "Id": "fp_StoryTime7",
        "Name": "Arano Restoration - Extraction",
        "Details": "Short Split Template",
        "Icon": "uixTxrSpot_DariusTalking"
    },
    "Weight": 1000,
    "InternalName": "StoryTime7",
    "PublishState": "PUBLISHED",
    "Difficulty": 6,
    "Requirements": [
        {
            "Scope": "Company",
            "RequirementTags": {
                "items": [
                    "flashpoint_StoryTime6_complete"
                ],
                "tagSetSourceFile": "Tags/CompanyTags"
            },
            "ExclusionTags": {
                "items": [
                    "flashpoint_StoryTime7_complete"
                ],
                "tagSetSourceFile": ""
            },
            "RequirementComparisons": []
        }
    ],
    "LocationRequirements": {
        "Scope": "StarSystem",
        "RequirementTags": {
            "items": [
				"planet_name_guldra"
			],
            "tagSetSourceFile": "Tags/PlanetNameTags"
        },
        "ExclusionTags": {
            "items": [],
            "tagSetSourceFile": ""
        },
        "RequirementComparisons": []
    },
    "PotentialEmployers": [
        "MercenaryReviewBoard"
    ],
    "TargetFaction": "NoFaction",
    "AllowRefitTime": true,
    "FlashpointLength": "SHORT",
    "Repeatable": false,
    "MilestoneSetID": "ms_fp_StoryTime7",
    "UseAvailableTimeoutOverride": false,
    "AvailableTimeout": 0,
    "UseInProgressTimeoutOverride": false,
    "InProgressTimeout": 0,
    "RewardCollectionID": "BTA_FP_ThreeRogueItemsG",
    "UnitDropTonnageHint": "None",
    "LanceDropTonnageHint": "None",
    "FlashpointShortDescription": "The Directorate has captured Lord Madeira, and we're going to get him back. We have his transponder coordinates, and we know that he's on the move. We're going to make planetfall, rescue Alexander, and recover the evidence he risked his life to bring us. And we will bring ruin to anyone who stands in our way.",
    "FlashpointDescriberCastDefId": "castDef_KameaDefault"
}
